Kirill_SerializerAndFuncs/Serializers_factory.py
Kirill_SerializerAndFuncs/__init__.py
Kirill_SerializerAndFuncs/base_serializer.py
Kirill_SerializerAndFuncs/dict_serializer.py
Kirill_SerializerAndFuncs/json_serializer.py
Kirill_SerializerAndFuncs/type_constants.py
Kirill_SerializerAndFuncs/xml_serializer.py
Kirill_SerializerAndFuncs-0.1.0.dist-info/METADATA
Kirill_SerializerAndFuncs-0.1.0.dist-info/WHEEL
Kirill_SerializerAndFuncs-0.1.0.dist-info/top_level.txt
Kirill_SerializerAndFuncs-0.1.0.dist-info/RECORD
