Metadata-Version: 2.1
Name: Kirill-SerializerAndFuncs
Version: 0.1.0
Summary: Library for class and function serialization
Author: KirillSysenkov
Author-email: k.halk@bk.ru
License: MIT
Classifier: Intended Audience :: Developers
Classifier: License :: OSI Approved :: MIT License
Classifier: Programming Language :: Python
Classifier: Programming Language :: Python :: 3
Classifier: Programming Language :: Python :: 3.6
Classifier: Programming Language :: Python :: 3.7
Classifier: Programming Language :: Python :: 3.8
Classifier: Programming Language :: Python :: 3.9
Classifier: Operating System :: OS Independent
Requires-Dist: regex
